wrapg/__init__.py
wrapg/snippet.py
wrapg/util.py
wrapg/wrapg.py
wrapg-0.2.8.dist-info/LICENSE
wrapg-0.2.8.dist-info/METADATA
wrapg-0.2.8.dist-info/WHEEL
wrapg-0.2.8.dist-info/top_level.txt
wrapg-0.2.8.dist-info/RECORD
