Metadata-Version: 2.1
Name: wrapg
Version: 0.2.8
Summary: Wrapper around psycopg3 using easy functions to interact with postgres.
Home-page: https://github.com/jturnercode/wrapg
Author: jturnercode
Author-email: jturner.code@gmail.com
Project-URL: Bug Tracker, https://github.com/jturnercode/wrapg/issues
Project-URL: Source Code, https://github.com/jturnercode/wrapg
Classifier: License :: OSI Approved :: MIT License
Classifier: Operating System :: OS Independent
Classifier: Intended Audience :: Developers
Classifier: Programming Language :: Python :: 3.10
Classifier: Topic :: Database
Requires-Python: >=3.10
License-File: LICENSE
Requires-Dist: psycopg[binary] >=3.0.11
Requires-Dist: pandas >=1.4.2
